{
    "data": {
        "values": [{
                "skill": "Javascript",
                "level": 4
            },
            {
                "skill": "HTML5",
                "level": 2
            },
            {
                "skill": "CSS",
                "level": 3
            },
            {
                "skill": "WebAssembly",
                "level": 2
            },
            {
                "skill": "XML",
                "level": 1
            }
        ]
    },
    "config": {
        "background": null
    },
    "mark": {
        "type": "bar",
        "color": "#fcfcfc",
        "stroke": "#222222"
    },
    "encoding": {
        "x": {
            "type": "quantitative",
            "field": "level",
            "title": null,
            "axis": {
                "labelExpr": "['★', '★★', '★★★', '★★★★'][datum.value - 1]",
                "labelAngle": -15
            }
        },
        "y": {
            "field": "skill",
            "title": null,
            "sort": "-x"
        }
    }
}